chirp_modbus.py
chirp_modbus-1.0.2.dist-info/LICENSE.txt
chirp_modbus-1.0.2.dist-info/METADATA
chirp_modbus-1.0.2.dist-info/WHEEL
chirp_modbus-1.0.2.dist-info/top_level.txt
chirp_modbus-1.0.2.dist-info/RECORD
