Metadata-Version: 2.1
Name: chirp-modbus
Version: 1.0.2
Summary: A wrapper library for communicatin with Modbus based Chirp soil moisture sensor
Home-page: https://github.com/Miceuz/rs485-moist-sensor
Author: Albertas Mickenas
Author-email: mic@wemakethings.net
License: Apache License, Version 2.0
Keywords: chirp,catnip,soil,moisture,sensor,rs485
Platform: UNKNOWN
Classifier: Development Status :: 5 - Production/Stable
Classifier: Intended Audience :: Developers
Classifier: Intended Audience :: Information Technology
Classifier: Intended Audience :: Science/Research
Classifier: Intended Audience :: Manufacturing
Classifier: License :: OSI Approved :: Apache Software License
Classifier: Natural Language :: English
Classifier: Operating System :: OS Independent
Classifier: Programming Language :: Python
Classifier: Topic :: Communications
Classifier: Topic :: Home Automation
Classifier: Topic :: Scientific/Engineering
Classifier: Topic :: Software Development :: Libraries
Classifier: Topic :: Software Development :: Libraries :: Python Modules
Classifier: Topic :: System :: Hardware :: Hardware Drivers
Classifier: Topic :: Terminals :: Serial
Requires-Dist: minimalmodbus (>=1.0.2)
